DecoID/DecoID.py
DecoID/__init__.py
DecoID/frac_shared_frag_log_reg_Negative.pkl
DecoID/frac_shared_frag_log_reg_Positive.pkl
DecoID/model.zip
DecoID/mzCloudCompound2TreeLinkage_InChIreference.pkl
DecoID/mzCloudCompound2TreeLinkageautoprocessing.pkl
DecoID/mzCloudCompound2TreeLinkagereference.pkl
DecoID/uniqueLosses.pkl
DecoID-0.3.2.dist-info/LICENSE.txt
DecoID-0.3.2.dist-info/METADATA
DecoID-0.3.2.dist-info/WHEEL
DecoID-0.3.2.dist-info/top_level.txt
DecoID-0.3.2.dist-info/RECORD
