Metadata-Version: 2.1
Name: DecoID
Version: 0.3.2
Summary: Metabolomics software for database assisted deconvolution of MS/MS spectra
Home-page: https://github.com/e-stan/DecoID
Author: Ethan Stancliffe
Author-email: estancl1234@gmail.com
License: MIT
Download-URL: https://github.com/e-stan/DecoID/archive/v0.3.2.tar.gz
Keywords: Metabolomics,Deconvolution,MS/MS,Metabolite ID
Platform: UNKNOWN
Classifier: Development Status :: 4 - Beta
Classifier: Intended Audience :: Developers
Classifier: Topic :: Software Development :: Build Tools
Classifier: License :: OSI Approved :: MIT License
Classifier: Programming Language :: Python :: 3.7
Requires-Dist: numpy
Requires-Dist: sklearn
Requires-Dist: pandas
Requires-Dist: dill
Requires-Dist: scipy
Requires-Dist: pyteomics
Requires-Dist: requests
Requires-Dist: lxml
Requires-Dist: molmass
Requires-Dist: keras
Requires-Dist: tensorflow
Requires-Dist: IsoSpecPy
